{
	"name": "rowandcolfunction",
	"properties": {
		"nbformat": 4,
		"nbformat_minor": 2,
		"bigDataPool": {
			"referenceName": "sparkkdspool",
			"type": "BigDataPoolReference"
		},
		"sessionProperties": {
			"driverMemory": "28g",
			"driverCores": 4,
			"executorMemory": "28g",
			"executorCores": 4,
			"numExecutors": 2,
			"conf": {
				"spark.dynamicAllocation.enabled": "false",
				"spark.dynamicAllocation.minExecutors": "2",
				"spark.dynamicAllocation.maxExecutors": "2",
				"spark.autotune.trackingId": "a56a27ba-c708-48b1-825e-e0c6f2e2657c"
			}
		},
		"metadata": {
			"saveOutput": true,
			"enableDebugMode": false,
			"kernelspec": {
				"name": "synapse_pyspark",
				"display_name": "Synapse PySpark"
			},
			"language_info": {
				"name": "python"
			},
			"a365ComputeOptions": {
				"id": "/subscriptions/c853d123-c274-4d76-8290-e704c4a8dd26/resourceGroups/AzurePracticeRG/providers/Microsoft.Synapse/workspaces/azurekdsynapsespark/bigDataPools/sparkkdspool",
				"name": "sparkkdspool",
				"type": "Spark",
				"endpoint": "https://azurekdsynapsespark.dev.azuresynapse.net/livyApi/versions/2019-11-01-preview/sparkPools/sparkkdspool",
				"auth": {
					"type": "AAD",
					"authResource": "https://dev.azuresynapse.net"
				},
				"sparkVersion": "3.4",
				"nodeCount": 10,
				"cores": 4,
				"memory": 28,
				"automaticScaleJobs": false
			},
			"sessionKeepAliveTimeout": 30
		},
		"cells": [
			{
				"cell_type": "code",
				"source": [
					"from pyspark.sql import *\r\n",
					"from pyspark.sql.functions import *\r\n",
					"from pyspark.sql.types import *\r\n",
					"row1= Row(name='Kanit', age=25)\r\n",
					"row2= Row(name='Devyani', age=26)\r\n",
					"data1=[row1,row2]\r\n",
					"print(row1.name)"
				],
				"execution_count": 28
			},
			{
				"cell_type": "code",
				"metadata": {
					"jupyter": {
						"source_hidden": false,
						"outputs_hidden": false
					},
					"nteract": {
						"transient": {
							"deleting": false
						}
					}
				},
				"source": [
					"spark.createDataFrame(data1).show()"
				],
				"execution_count": 29
			},
			{
				"cell_type": "code",
				"metadata": {
					"jupyter": {
						"source_hidden": false,
						"outputs_hidden": false
					},
					"nteract": {
						"transient": {
							"deleting": false
						}
					}
				},
				"source": [
					"person=Row('name','salary')\r\n",
					"person1=person('Kanit',1000)\r\n",
					"person2=person('Ankit',2000)\r\n",
					"data2=[person1,person2]\r\n",
					"print(person2.name)\r\n",
					"spark.createDataFrame(data2).show()"
				],
				"execution_count": 33
			},
			{
				"cell_type": "code",
				"metadata": {
					"jupyter": {
						"source_hidden": false,
						"outputs_hidden": false
					},
					"nteract": {
						"transient": {
							"deleting": false
						}
					},
					"collapsed": false
				},
				"source": [
					"data1=[(1,\"kanit\",1000),(2,\"das\",2000)]\r\n",
					"schema1=[\"id\",\"name\",'salary']\r\n",
					"df=spark.createDataFrame(data=data1,schema=schema1)\r\n",
					"df.show()\r\n",
					"df.withColumn('new sal',lit(5000)).show()"
				],
				"execution_count": 38
			}
		]
	}
}